gatherchat_agent_sdk/__init__.py
gatherchat_agent_sdk/agent.py
gatherchat_agent_sdk/auth.py
gatherchat_agent_sdk/client.py
gatherchat_agent_sdk/simple_agent.py
gatherchat_agent_sdk-1.0.0.dist-info/licenses/LICENSE
gatherchat_agent_sdk-1.0.0.dist-info/METADATA
gatherchat_agent_sdk-1.0.0.dist-info/WHEEL
gatherchat_agent_sdk-1.0.0.dist-info/top_level.txt
gatherchat_agent_sdk-1.0.0.dist-info/RECORD
